{"post_id":"WMC:E14000750","post_label":"Holborn and St Pancras","election":"parl.2017-06-08","candidates":[{"id":"8005","name":"Timothy Barnes","party_id":"party:52","party_name":"Conservative and Unionist Party","elected":"","twitter_username":"CampaignTim","homepage_url":"https:\/\/timothybarnes.org\/","party_ec_id":"PP52"},{"id":"34835","name":"Si\u00e2n Berry","party_id":"party:63","party_name":"Green Party","elected":"","email":"action@sianberry.london","twitter_username":"sianberry","facebook_page_url":"https:\/\/www.facebook.com\/sianberrygreen\/","party_ppc_page_url":"https:\/\/my.greenparty.org.uk\/candidates\/106004","facebook_personal_url":"https:\/\/www.facebook.com\/sianberryhome","homepage_url":"http:\/\/sianberry.london\/","wikipedia_url":"https:\/\/en.wikipedia.org\/wiki\/Si%C3%A2n_Berry","linkedin_url":"https:\/\/www.linkedin.com\/in\/sian-berry-23917524\/","image_url":"https:\/\/candidates.democracyclub.org.uk\/media\/images\/images\/7452.png","party_ec_id":"PP63"},{"id":"25400","name":"Stephen Crosher","party_id":"party:90","party_name":"Liberal Democrats","elected":"","email":"stephen@stephencrosher.co.uk","twitter_username":"StephenCrosher","facebook_page_url":"https:\/\/www.facebook.com\/CamdenLibDems\/","facebook_personal_url":"https:\/\/www.facebook.com\/stephen.crosher.5","homepage_url":"https:\/\/ldcamden.nationbuilder.com\/stephen_crosher","image_url":"https:\/\/candidates.democracyclub.org.uk\/media\/images\/images\/25400.png","party_ec_id":"PP90"},{"id":"25402","name":"Giles Game","party_id":"party:85","party_name":"UK Independence Party (UKIP)","elected":"","party_ec_id":"PP85"},{"id":"1528","name":"Janus Polenceus","party_id":"party:17","party_name":"English Democrats","elected":"","email":"Democracyintheuk@gmail.com","facebook_personal_url":"https:\/\/www.facebook.com\/Vote-Janus-Polenceus-English-Democrats-Party-2017-1871781126405139\/","image_url":"https:\/\/candidates.democracyclub.org.uk\/media\/images\/images\/1528.png","party_ec_id":"PP17"},{"id":"5077","name":"Keir Starmer","party_id":"party:53","party_name":"Labour Party","elected":"","email":"keir_starmer@labour.org.uk","twitter_username":"Keir_Starmer","homepage_url":"http:\/\/www.keirstarmer.com\/","wikipedia_url":"http:\/\/en.wikipedia.org\/wiki\/Keir_Starmer","image_url":"https:\/\/candidates.democracyclub.org.uk\/media\/images\/55323ec329c5d53959d9e45f.png","parlparse_id":"uk.org.publicwhip\/person\/25353","theyworkforyou_url":"http:\/\/www.theyworkforyou.com\/mp\/25353","party_ec_id":"PP53"}]}