{"post_id":"WMC:E14000974","post_label":"Stoke-on-Trent South","election":"parl.2017-06-08","candidates":[{"id":"19836","name":"Jack Brereton","party_id":"party:52","party_name":"Conservative and Unionist Party","elected":"","email":"jack@jackbrereton.co.uk","twitter_username":"ToryPressMids","facebook_page_url":"https:\/\/www.facebook.com\/jackbreretonforstoke\/","party_ppc_page_url":"https:\/\/stokeconservatives.com\/cllr-jack-brereton\/","homepage_url":"http:\/\/www.jackbrereton.co.uk\/","image_url":"https:\/\/candidates.democracyclub.org.uk\/media\/images\/images\/19836.png","party_ec_id":"PP52"},{"id":"3387","name":"Rob Flello","party_id":"party:53","party_name":"Labour Party","elected":"","email":"robflello@hotmail.com","twitter_username":"RobFlelloMP","facebook_page_url":"https:\/\/www.facebook.com\/RobFlelloStokeSouth\/","party_ppc_page_url":"https:\/\/vote.labour.org.uk\/rob-flello","homepage_url":"http:\/\/www.robertflello.com\/","wikipedia_url":"https:\/\/en.wikipedia.org\/wiki\/Rob_Flello","image_url":"https:\/\/candidates.democracyclub.org.uk\/media\/images\/553b425fe6d2cbcd26e36a25.png","parlparse_id":"uk.org.publicwhip\/person\/11843","theyworkforyou_url":"http:\/\/www.theyworkforyou.com\/mp\/11843","party_ec_id":"PP53"},{"id":"5233","name":"Zablocki Jan","party_id":"party:63","party_name":"Green Party","elected":"False","email":"jan.northmidscwu@btconnect.com","twitter_username":"ZablockiJan","party_ppc_page_url":"https:\/\/my.greenparty.org.uk\/candidates\/106226","image_url":"https:\/\/candidates.democracyclub.org.uk\/media\/images\/55487865cce2c20e27fea5e4.png","party_ec_id":"PP63"},{"id":"5462","name":"Ian Wilkes","party_id":"party:90","party_name":"Liberal Democrats","elected":"False","email":"ian.wilkes@newcastlelibdems.org.uk","twitter_username":"nullibdems","facebook_page_url":"https:\/\/www.facebook.com\/pages\/Ian-Wilkes-for-Newcastle-under-Lyme\/1567330856860397","party_ppc_page_url":"http:\/\/www.libdems.org.uk\/ian_wilkes","homepage_url":"http:\/\/www.newcastlelibdems.org.uk\/ian-wilkes-for-newcastle\/","image_url":"https:\/\/candidates.democracyclub.org.uk\/media\/images\/55474695a534c89955aeff6b.png","party_ec_id":"PP90"}]}