{"post_id":"WMC:E14000871","post_label":"Oldham West and Royton","election":"parl.2017-06-08","candidates":[{"id":"35140","name":"Christopher Glenny","party_id":"party:52","party_name":"Conservative and Unionist Party","elected":"False","party_ec_id":"PP52"},{"id":"4520","name":"Garth Harkness","party_id":"party:90","party_name":"Liberal Democrats","elected":"","email":"Garth.harkness@gmail.com","twitter_username":"garthharkness","party_ppc_page_url":"http:\/\/www.libdems.org.uk\/garth_harkness","homepage_url":"http:\/\/garthharkness.mycouncillor.org.uk\/","linkedin_url":"https:\/\/www.linkedin.com\/pub\/garth-harkness\/5a\/370\/785","image_url":"https:\/\/candidates.democracyclub.org.uk\/media\/images\/5481e937b150e238702c0646.png","party_ec_id":"PP90"},{"id":"14929","name":"Ruth Keating","party_id":"party:85","party_name":"UK Independence Party (UKIP)","elected":"False","party_ec_id":"PP85"},{"id":"14897","name":"Adam King","party_id":"party:63","party_name":"Green Party","elected":"False","email":"adam.king@greenparty.org.uk","twitter_username":"AdamKing_Green","facebook_page_url":"https:\/\/www.facebook.com\/AdamKingMCR\/","party_ppc_page_url":"https:\/\/my.greenparty.org.uk\/candidates\/106125","homepage_url":"http:\/\/manchestergreenparty.org.uk\/","image_url":"https:\/\/candidates.democracyclub.org.uk\/media\/images\/images\/14897.png","party_ec_id":"PP63"},{"id":"34144","name":"Jim McMahon","party_id":"joint-party:53-119","party_name":"Labour and Co-operative Party","elected":"","email":"jim_mcmahon@labour.org.uk","twitter_username":"JimfromOldham","facebook_page_url":"https:\/\/www.facebook.com\/jimfromoldham\/","party_ppc_page_url":"https:\/\/party.coop\/person\/jim-mcmahon\/","homepage_url":"http:\/\/vote.labour.org.uk\/jim-mcmahon","wikipedia_url":"https:\/\/en.wikipedia.org\/wiki\/Jim_McMahon_(politician)","image_url":"https:\/\/candidates.democracyclub.org.uk\/media\/images\/images\/34144.png"}]}