{"post_id":"WMC:E14000972","post_label":"Stoke-on-Trent Central","election":"parl.2017-06-08","candidates":[{"id":"3488","name":"Peter Andras","party_id":"party:90","party_name":"Liberal Democrats","elected":"","email":"peter.andras.ld@googlemail.com","twitter_username":"peterandrasncl","image_url":"https:\/\/s3.eu-west-2.amazonaws.com\/static-candidates.democracyclub.org.uk\/media\/images\/images\/76128-6a07a5d6-bd2e-40a4-8f73-aa725ae23b43.png","party_ec_id":"PP90"},{"id":"5906","name":"Mick Harold","party_id":"party:85","party_name":"UK Independence Party (UKIP)","elected":"","email":"mick.harold@ukiplocal.org","party_ec_id":"PP85"},{"id":"19838","name":"Adam William Colclough","party_id":"party:63","party_name":"Green Party","elected":"","email":"colclougha@aol.com","twitter_username":"adam_colclougha","facebook_personal_url":"https:\/\/www.facebook.com\/adam.colclough.9","image_url":"https:\/\/s3.eu-west-2.amazonaws.com\/static-candidates.democracyclub.org.uk\/media\/images\/images\/19838.png","party_ec_id":"PP63"},{"id":"19840","name":"Barbara Fielding","party_id":"ynmp-party:2","party_name":"Independent","elected":"","party_ec_id":"ynmp-party:2"},{"id":"19842","name":"Gareth Snell","party_id":"joint-party:53-119","party_name":"Labour and Co-operative Party","elected":"True","email":"garethstokecentral@outlook.com","facebook_page_url":"https:\/\/www.facebook.com\/garethforstoke\/","party_ppc_page_url":"https:\/\/party.coop\/person\/gareth-snell-mp\/","homepage_url":"http:\/\/www.garethsnell.org.uk\/","wikipedia_url":"https:\/\/en.wikipedia.org\/wiki\/Gareth_Snell","image_url":"https:\/\/s3.eu-west-2.amazonaws.com\/static-candidates.democracyclub.org.uk\/media\/images\/images\/19842_24hSIUx.png","parlparse_id":"uk.org.publicwhip\/person\/25601","theyworkforyou_url":"https:\/\/www.theyworkforyou.com\/mp\/25601\/","party_ec_id":"joint-party:53-119"},{"id":"34325","name":"Daniel Jellyman","party_id":"party:52","party_name":"Conservative and Unionist Party","elected":"","email":"stokeconservatives@live.co.uk","twitter_username":"DanielJellyman","party_ppc_page_url":"https:\/\/www.conservatives.com\/OurTeam\/Prospective-Parliamentary-Candidates\/Jellyman-Daniel","image_url":"https:\/\/s3.eu-west-2.amazonaws.com\/static-candidates.democracyclub.org.uk\/media\/images\/images\/34325.png","party_ec_id":"PP52"}]}