{"post_id":"WMC:W07000062","post_label":"Clwyd South","election":"parl.2017-06-08","candidates":[{"id":"34377","name":"Chris Allen","party_id":"party:77","party_name":"Plaid Cymru - The Party of Wales","elected":"","twitter_username":"plaidcymruchris","party_ppc_page_url":"https:\/\/twitter.com\/plaiddeclwydsth","facebook_personal_url":"https:\/\/www.facebook.com\/chris.allen.900","image_url":"https:\/\/candidates.democracyclub.org.uk\/media\/images\/images\/34377.png","party_ec_id":"PP77"},{"id":"9175","name":"Jeanette Stefani Bassford-Barton","party_id":"party:85","party_name":"UK Independence Party (UKIP)","elected":"","image_url":"https:\/\/candidates.democracyclub.org.uk\/media\/images\/images\/9175.png","party_ec_id":"PP85"},{"id":"26974","name":"Simon Baynes","party_id":"party:52","party_name":"Conservative and Unionist Party","elected":"","email":"baynes@bodfach.com","twitter_username":"baynes_simon","facebook_page_url":"https:\/\/www.facebook.com\/SimonBaynesforClwydSouth\/","party_ppc_page_url":"https:\/\/www.conservatives.com\/OurTeam\/Prospective-Parliamentary-Candidates\/Baynes-Simon","homepage_url":"http:\/\/www.simonbaynes.co.uk\/","image_url":"https:\/\/candidates.democracyclub.org.uk\/media\/images\/images\/26974.png","party_ec_id":"PP52"},{"id":"2700","name":"Susan Elan Jones","party_id":"party:53","party_name":"Labour Party","elected":"","email":"susanclwydsouth@gmail.com","twitter_username":"susanelanjones","facebook_page_url":"https:\/\/www.facebook.com\/susan4clwydsouth\/","party_ppc_page_url":"http:\/\/www.welshlabour.wales\/susan_elan_jones_mp","homepage_url":"http:\/\/www.susanelanjones.co.uk\/","wikipedia_url":"http:\/\/en.wikipedia.org\/wiki\/Susan_Jones","image_url":"https:\/\/candidates.democracyclub.org.uk\/media\/images\/55350fe9b247335574a42e76.png","parlparse_id":"uk.org.publicwhip\/person\/24720","theyworkforyou_url":"http:\/\/www.theyworkforyou.com\/mp\/24720","party_ec_id":"PP53"},{"id":"2441","name":"Bruce Roberts","party_id":"party:90","party_name":"Liberal Democrats","elected":"","email":"politics@bruceroberts.plus.com","twitter_username":"WxmBruce","party_ppc_page_url":"http:\/\/www.welshlibdems.wales\/bruce_roberts","image_url":"https:\/\/candidates.democracyclub.org.uk\/media\/images\/54cd1c26668e142f73d3b4bd.png","party_ec_id":"PP90"}]}