{"post_id":"WMC:E14000583","post_label":"Bosworth","election":"parl.2015-05-07","candidates":[{"id":"385","name":"David Tredinnick","party_id":"party:52","party_name":"Conservative and Unionist Party","elected":"True","email":"tredinnickd@parliament.uk","party_ppc_page_url":"https:\/\/www.conservatives.com\/OurTeam\/Prospective_Parliamentary_Candidates\/Tredinnick_David.aspx","homepage_url":"http:\/\/www.davidtredinnickmp.com\/","wikipedia_url":"https:\/\/en.wikipedia.org\/wiki\/David_Tredinnick_%28politician%29","image_url":"https:\/\/s3.eu-west-2.amazonaws.com\/static-candidates.democracyclub.org.uk\/media\/images\/images\/385.png","parlparse_id":"uk.org.publicwhip\/person\/10602","theyworkforyou_url":"https:\/\/www.theyworkforyou.com\/mp\/10602\/","party_ec_id":"PP52"},{"id":"388","name":"Michael Mullaney","party_id":"party:90","party_name":"Liberal Democrats","elected":"","email":"michaeltmullaney@yahoo.co.uk","twitter_username":"miketmullaney","facebook_page_url":"https:\/\/www.facebook.com\/MichaelMullaneyForBosworth","facebook_personal_url":"https:\/\/www.facebook.com\/michael.mullaney.12","homepage_url":"http:\/\/bosworthlibdems.org.uk\/","image_url":"https:\/\/s3.eu-west-2.amazonaws.com\/static-candidates.democracyclub.org.uk\/media\/images\/5481e8d1b150e238702c0603.png","party_ec_id":"PP90"},{"id":"4773","name":"Chris Kealey","party_id":"party:53","party_name":"Labour Party","elected":"","email":"bosworthlabour@gmail.com","twitter_username":"_ChrisKealey","facebook_page_url":"http:\/\/www.facebook.com\/kealey4bosworth","party_ppc_page_url":"http:\/\/www.labour.org.uk\/people\/detail\/chris-kealey","facebook_personal_url":"https:\/\/facebook.com\/kealey4bosworth","homepage_url":"http:\/\/www.kealey4bosworth.co.uk\/","image_url":"https:\/\/s3.eu-west-2.amazonaws.com\/static-candidates.democracyclub.org.uk\/media\/images\/images\/4773.png","party_ec_id":"PP53"},{"id":"4992","name":"David Sprason","party_id":"party:85","party_name":"UK Independence Party (UKIP)","elected":"","email":"david@ukipleicestershire.org","twitter_username":"ruraloutback","homepage_url":"http:\/\/ukipleicestershire.org\/","image_url":"https:\/\/s3.eu-west-2.amazonaws.com\/static-candidates.democracyclub.org.uk\/media\/images\/images\/4992.png","party_ec_id":"PP85"}]}