{"post_id":"WMC:E14000866","post_label":"Nottingham North","election":"parl.2015-05-07","candidates":[{"id":"3611","name":"Graham Allen","party_id":"party:53","party_name":"Labour Party","elected":"True","email":"allen@nottinghamlabour.org.uk","twitter_username":"GrahamAllenMPX","homepage_url":"http:\/\/grahamallenmp.co.uk\/","wikipedia_url":"https:\/\/en.wikipedia.org\/wiki\/Graham_Allen_%28politician%29","image_url":"https:\/\/candidates.democracyclub.org.uk\/media\/images\/images\/3611.png","parlparse_id":"uk.org.publicwhip\/person\/10008","theyworkforyou_url":"http:\/\/www.theyworkforyou.com\/mp\/10008","party_ec_id":"PP53"},{"id":"5783","name":"Kat Boettge","party_id":"party:63","party_name":"Green Party","elected":"False","email":"katharina.boettge@greenparty.org.uk","twitter_username":"KatBoettge","party_ppc_page_url":"https:\/\/my.greenparty.org.uk\/candidates\/106119","facebook_personal_url":"https:\/\/www.facebook.com\/katharina.boettge","image_url":"https:\/\/candidates.democracyclub.org.uk\/media\/images\/553c9e6fdcfe1d5b5cf81468.png","party_ec_id":"PP63"},{"id":"4222","name":"Louise Burfitt-Dons","party_id":"party:52","party_name":"Conservative and Unionist Party","elected":"False","email":"louise@nottinghamconservatives.co.uk","twitter_username":"LouiseBurfDons","facebook_page_url":"https:\/\/www.facebook.com\/louiseburfittdons","party_ppc_page_url":"https:\/\/www.conservatives.com\/OurTeam\/Prospective_Parliamentary_Candidates\/Burfitt-Dons.aspx","homepage_url":"http:\/\/www.louiseburfittdons.com\/","wikipedia_url":"https:\/\/en.wikipedia.org\/wiki\/Louise_Burfitt-Dons","image_url":"https:\/\/candidates.democracyclub.org.uk\/media\/images\/54fe20e01ccf185f0d8cc4d5.png","party_ec_id":"PP52"},{"id":"4673","name":"Stephen Crosby","party_id":"party:85","party_name":"UK Independence Party (UKIP)","elected":"False","email":"Stephen.crosby@ni.ukiplocal.org","twitter_username":"stephen_crosby1","facebook_page_url":"https:\/\/www.facebook.com\/StrangfordUKIP\/","party_ppc_page_url":"http:\/\/www.margotparkermep.uk\/margot-parker-praise-for-latest-nottingham-candidate\/","facebook_personal_url":"https:\/\/www.facebook.com\/stephen.crosby.54","homepage_url":"https:\/\/ukipnottingham.org\/","image_url":"https:\/\/candidates.democracyclub.org.uk\/media\/images\/54fdecb61ccf185f0d8cc4c3.png","party_ec_id":"PP85"},{"id":"6627","name":"Catherine Meadows","party_id":"party:804","party_name":"Trade Unionist and Socialist Coalition","elected":"False","email":"cmeadowstuscelection@gmail.com","party_ppc_page_url":"http:\/\/tusc2015.com\/cathy-meadows-for-nottingham-north2\/","image_url":"https:\/\/candidates.democracyclub.org.uk\/media\/images\/553a66c310a500d1762bf1bf.png","party_ec_id":"PP804"},{"id":"5684","name":"Tony Sutton","party_id":"party:90","party_name":"Liberal Democrats","elected":"False","email":"tonysutton.libdem@btinternet.com","twitter_username":"TonySutton4Nott","party_ppc_page_url":"http:\/\/www.libdems.org.uk\/tony_sutton","image_url":"https:\/\/candidates.democracyclub.org.uk\/media\/images\/553be5ffa51642637514d64d.png","party_ec_id":"PP90"}]}