{"post_id":"WMC:E14001042","post_label":"Windsor","election":"parl.2015-05-07","candidates":[{"id":"4114","name":"Adam Afriyie","party_id":"party:52","party_name":"Conservative and Unionist Party","elected":"True","email":"office@windsorconservatives.com","twitter_username":"AdamAfriyie","party_ppc_page_url":"https:\/\/www.conservatives.com\/OurTeam\/Prospective_Parliamentary_Candidates\/Afriyie_Adam.aspx","facebook_personal_url":"https:\/\/www.facebook.com\/adam.afriyie.7","homepage_url":"http:\/\/adamafriyie.org\/","wikipedia_url":"http:\/\/en.wikipedia.org\/wiki\/Adam_Afriyie","image_url":"https:\/\/candidates.democracyclub.org.uk\/media\/images\/553aa79a319151d456c24fac.png","parlparse_id":"uk.org.publicwhip\/person\/11929","theyworkforyou_url":"http:\/\/www.theyworkforyou.com\/mp\/11929","party_ec_id":"PP52"},{"id":"7146","name":"Wisdom Methodious Da Costa","party_id":"ynmp-party:2","party_name":"Independent","elected":"False","email":"wisdomdacosta@hotmail.co.uk","twitter_username":"wisdomdacosta","facebook_page_url":"https:\/\/www.facebook.com\/CllrWisdomDaCosta","homepage_url":"http:\/\/www.wisdomforwindsormp.org\/","linkedin_url":"https:\/\/uk.linkedin.com\/pub\/wisdom-da-costa\/14\/a91\/27","image_url":"https:\/\/candidates.democracyclub.org.uk\/media\/images\/55225106328bff5d39338a3c.png"},{"id":"4468","name":"Fiona Dent","party_id":"party:53","party_name":"Labour Party","elected":"False","email":"Fionadentlabour@gmail.com","twitter_username":"FionaDentLabour","party_ppc_page_url":"http:\/\/www.labour.org.uk\/people\/detail\/fiona-dent","facebook_personal_url":"https:\/\/www.facebook.com\/FionaDentLabour\/","homepage_url":"http:\/\/www.fionadentlabour.com\/","image_url":"https:\/\/candidates.democracyclub.org.uk\/media\/images\/5481e8b7b150e238702c05f1.png","party_ec_id":"PP53"},{"id":"6491","name":"George Fussey","party_id":"party:90","party_name":"Liberal Democrats","elected":"False","email":"george.fussey@gmail.com","twitter_username":"GeorgeFussey","party_ppc_page_url":"http:\/\/www.libdems.org.uk\/george_fussey","linkedin_url":"https:\/\/www.linkedin.com\/pub\/george-fussey\/2a\/633\/8","image_url":"https:\/\/candidates.democracyclub.org.uk\/media\/images\/553c9fa0dcfe1d5b5cf8146b.png","party_ec_id":"PP90"},{"id":"6765","name":"Tariq Malik","party_id":"party:85","party_name":"UK Independence Party (UKIP)","elected":"False","email":"ukipwindsor@outlook.com","party_ec_id":"PP85"},{"id":"2836","name":"Derek Wall","party_id":"party:63","party_name":"Green Party","elected":"False","email":"wallddd@hotmail.com","twitter_username":"Anothergreen","party_ppc_page_url":"https:\/\/eastberkshire.greenparty.org.uk\/news\/derek-wall-selected-to-challenge-theresa-may-in-maidenhead.html","homepage_url":"http:\/\/another-green-world.blogspot.co.uk\/","wikipedia_url":"http:\/\/en.wikipedia.org\/wiki\/Derek_Wall","image_url":"https:\/\/candidates.democracyclub.org.uk\/media\/images\/5516dd85929f1bbe286be049.png","party_ec_id":"PP63"}]}