{"countInfo":{"valid_poll":"53630","total_poll":"55138","post_label":"Dewsbury","post_id":"E14000666","electorate":"79770","rejected":1508},"countGroup":[{"id":"7002","votes":"22406","elected":"","name":"Richard Carter","post_id":"E14000666","party_name":"Yorkshire First"},{"id":"3837","votes":"20955","elected":"","name":"Adrian Cruden","post_id":"E14000666","party_name":"Green Party"},{"id":"6489","votes":"6649","elected":"","name":"Steve Hakes","post_id":"E14000666","party_name":"Christian Peoples Alliance"},{"id":"6361","votes":"1924","elected":"","name":"Ednan Hussain","post_id":"E14000666","party_name":"Liberal Democrats"},{"id":"1609","votes":"1366","elected":"","name":"Simon Reevell","post_id":"E14000666","party_name":"Conservative and Unionist Party"},{"id":"4319","votes":"236","elected":"","name":"Paula Sherriff","post_id":"E14000666","party_name":"Labour Party"},{"id":"2348","votes":"94","elected":"","name":"Mark Thackray","post_id":"E14000666","party_name":"UK Independence Party (UKIP)"}]}