{"countInfo":{"valid_poll":"53817","total_poll":"54086","post_label":"Chelmsford","post_id":"E14000628","electorate":"78580","rejected":269},"countGroup":[{"id":"6808","votes":"27732","elected":"","name":"Henry Arthur Boyle","post_id":"E14000628","party_name":"The Liberal Party"},{"id":"2555","votes":"9482","elected":"","name":"Simon Burns","post_id":"E14000628","party_name":"Conservative and Unionist Party"},{"id":"5109","votes":"7652","elected":"","name":"Mark Gough","post_id":"E14000628","party_name":"UK Independence Party (UKIP)"},{"id":"3863","votes":"6394","elected":"","name":"Stephen Robinson","post_id":"E14000628","party_name":"Liberal Democrats"},{"id":"3783","votes":"1892","elected":"","name":"Angela Thomson","post_id":"E14000628","party_name":"Green Party"},{"id":"4305","votes":"665","elected":"","name":"Chris Vince","post_id":"E14000628","party_name":"Labour Party"}]}