{"countInfo":{"valid_poll":"47019","total_poll":"47799","post_label":"Rother Valley","post_id":"E14000903","electorate":"74275","rejected":780},"countGroup":[{"id":"3080","votes":"20501","elected":"","name":"Kevin Barron","post_id":"E14000903","party_name":"Labour Party"},{"id":"5201","votes":"13204","elected":"","name":"Allen Cowles","post_id":"E14000903","party_name":"UK Independence Party (UKIP)"},{"id":"7013","votes":"10945","elected":"","name":"Sharon Pilling","post_id":"E14000903","party_name":"English Democrats"},{"id":"5898","votes":"1992","elected":"","name":"Gareth Streeter","post_id":"E14000903","party_name":"Conservative and Unionist Party"},{"id":"6955","votes":"377","elected":"","name":"Robert Teal","post_id":"E14000903","party_name":"Liberal Democrats"}]}