{"countInfo":{"valid_poll":"37992","total_poll":"38341","post_label":"Dudley North","post_id":"E14000671","electorate":"60717","rejected":349},"countGroup":[{"id":"7352","votes":"15885","elected":"","name":"Rehan Afzal","post_id":"E14000671","party_name":"Apni Party"},{"id":"4148","votes":"11704","elected":"","name":"Ian Austin","post_id":"E14000671","party_name":"Labour Party"},{"id":"1997","votes":"9113","elected":"","name":"Mike Collins","post_id":"E14000671","party_name":"Liberal Democrats"},{"id":"6140","votes":"517","elected":"","name":"Will Duckworth","post_id":"E14000671","party_name":"Green Party"},{"id":"4797","votes":"478","elected":"","name":"Bill Etheridge","post_id":"E14000671","party_name":"UK Independence Party (UKIP)"},{"id":"7022","votes":"156","elected":"","name":"Les Jones","post_id":"E14000671","party_name":"Conservative and Unionist Party"},{"id":"6167","votes":"139","elected":"","name":"David Pitt","post_id":"E14000671","party_name":"Trade Unionist and Socialist Coalition"}]}