{"countInfo":{"valid_poll":"47665","total_poll":"47788","post_label":"Gosport","post_id":"E14000713","electorate":"73268","rejected":123},"countGroup":[{"id":"34758","votes":"26364","elected":"","name":"Monica Cassidy","post_id":"E14000713","party_name":"Green Party"},{"id":"2937","votes":"9266","elected":"","name":"Caroline Dinenage","post_id":"E14000713","party_name":"Conservative and Unionist Party"},{"id":"5876","votes":"6926","elected":"","name":"Alan Durrant","post_id":"E14000713","party_name":"Labour Party"},{"id":"2359","votes":"3298","elected":"","name":"Rob Hylands","post_id":"E14000713","party_name":"Liberal Democrats"},{"id":"7438","votes":"1707","elected":"","name":"Jeffrey Roberts","post_id":"E14000713","party_name":"Independent"},{"id":"5282","votes":"104","elected":"","name":"Christopher Wood","post_id":"E14000713","party_name":"UK Independence Party (UKIP)"}]}