{"countInfo":{"valid_poll":"40556","total_poll":"40837","post_label":"Preseli Pembrokeshire","post_id":"W07000065","electorate":"57291","rejected":281},"countGroup":[{"id":"5796","votes":"16383","elected":"","name":"Frances Bryant","post_id":"W07000065","party_name":"Green Party"},{"id":"425","votes":"11414","elected":"","name":"Stephen Crabb","post_id":"W07000065","party_name":"Conservative and Unionist Party"},{"id":"5526","votes":"4257","elected":"","name":"Howard Lillyman","post_id":"W07000065","party_name":"UK Independence Party (UKIP)"},{"id":"7327","votes":"3729","elected":"","name":"Rodney Maile","post_id":"W07000065","party_name":"The New Society of Worth"},{"id":"4404","votes":"2518","elected":"","name":"Paul Miller","post_id":"W07000065","party_name":"Labour Party"},{"id":"4955","votes":"1452","elected":"","name":"John Osmond","post_id":"W07000065","party_name":"Plaid Cymru - The Party of Wales"},{"id":"6623","votes":"780","elected":"","name":"Chris Overton","post_id":"W07000065","party_name":"Independent Save Withybush Save Lives"},{"id":"6699","votes":"23","elected":"","name":"Nick Tregoning","post_id":"W07000065","party_name":"Liberal Democrats"}]}