{"countInfo":{"valid_poll":"33618","total_poll":"33982","post_label":"Swansea East","post_id":"W07000048","electorate":"58011","rejected":364},"countGroup":[{"id":"5787","votes":"17807","elected":"","name":"Carolyn Harris","post_id":"W07000048","party_name":"Labour Party"},{"id":"5647","votes":"5779","elected":"","name":"Altaf Hussain","post_id":"W07000048","party_name":"Conservative and Unionist Party"},{"id":"5028","votes":"5142","elected":"","name":"Amina Jamal","post_id":"W07000048","party_name":"Liberal Democrats"},{"id":"5865","votes":"3498","elected":"","name":"Clifford Johnson","post_id":"W07000048","party_name":"UK Independence Party (UKIP)"},{"id":"2395","votes":"1392","elected":"","name":"Dic Jones","post_id":"W07000048","party_name":"Plaid Cymru - The Party of Wales"}]}